{
  "PortFolio": [
    {
      "id": "352ea241-8622-4aae-8ef1-53b5b24be92f",
      "name_project": "AzMovie",
      "about_project": "Tous vos films de A à Z",
      "link_project_github": "github",
      "link_projects": "www.abc.com"
    },
    {
      "id": "7eb071ca-ad78-4e78-ae6c-97052ce4e9b8",
      "name_project": "Christopher",
      "about_project": "Tous vos films de A à Z",
      "link_project_github": "github",
      "link_projects": "www.abc.com"
    },
    {
      "id": "8bc53586-133e-48e6-a2f0-61a66ad2d841",
      "name_project": "Merdie",
      "about_project": "Tous vos films de A à Z",
      "link_project_github": "github",
      "link_projects": "www.abc.com"
    },
    {
      "id": "9250a984-9acb-4e52-9749-9f05fab36f77",
      "name_project": "Netflix",
      "about_project": "Site qui presente mes realisation",
      "link_project_github": "github",
      "link_projects": "www.netflix.com"
    }
  ]
}
